LICENSE.txt
MANIFEST.in
driver1_params.txt
ez_setup.py
requirements.txt
setup.cfg
setup.py
TheLandlab.egg-info/PKG-INFO
TheLandlab.egg-info/SOURCES.txt
TheLandlab.egg-info/dependency_links.txt
TheLandlab.egg-info/entry_points.txt
TheLandlab.egg-info/top_level.txt
docs/index/landlab_master_index.txt
docs/model_grid_guide/test_inputs_for_diffusion_model.txt
landlab/__init__.py
landlab/components/__init__.py
landlab/components/diff_2d.py
landlab/components/sample.py
landlab/components/PET/__init__.py
landlab/components/PET/potential_evapotranspiration_field.py
landlab/components/cellular_automata/__init__.py
landlab/components/cellular_automata/hex_lca.py
landlab/components/cellular_automata/landlab_ca.py
landlab/components/cellular_automata/oriented_hex_lca.py
landlab/components/cellular_automata/oriented_raster_lca.py
landlab/components/cellular_automata/raster_lca.py
landlab/components/cellular_automata/boundaries/__init__.py
landlab/components/cellular_automata/boundaries/hex_lattice_tectonicizer.py
landlab/components/craters/__init__.py
landlab/components/craters/component.py
landlab/components/craters/craters.py
landlab/components/craters/dig_craters.py
landlab/components/craters/dig_craters_copy.py
landlab/components/dem_support/__init__.py
landlab/components/dem_support/dem_boundary_conditions.py
landlab/components/detachment_ltd_sed_trp/__init__.py
landlab/components/detachment_ltd_sed_trp/generate_detachment_ltd_transport.py
landlab/components/diffusion/__init__.py
landlab/components/diffusion/diffusion.py
landlab/components/diffusion/diffusion_model.py
landlab/components/fire_generator/__init__.py
landlab/components/fire_generator/generate_fire.py
landlab/components/flexure/__init__.py
landlab/components/flexure/cfuncs.c
landlab/components/flexure/flexure.py
landlab/components/flexure/funcs.py
landlab/components/flow_accum/__init__.py
landlab/components/flow_accum/flow_accum_bw.py
landlab/components/flow_accum/flow_accumulation.py
landlab/components/flow_accum/flow_accumulation2.py
landlab/components/flow_routing/__init__.py
landlab/components/flow_routing/flow_direction_DN.py
landlab/components/flow_routing/flow_routing_D8.py
