Metadata-Version: 1.0
Name: TheLandlab
Version: 0.1.5
Summary: Plugin-based component modeling tool.
Home-page: https://csdms.colorado.edu/trac/landlab
Author: Eric Hutton
Author-email: eric.hutton@colorado.edu
License: UNKNOWN
Platform: UNKNOWN
